tracery/__init__.py
tracery/__main__.py
tracery/modifiers.py
tracery/py.typed
tracery3-1.0.1.dist-info/LICENSE
tracery3-1.0.1.dist-info/METADATA
tracery3-1.0.1.dist-info/WHEEL
tracery3-1.0.1.dist-info/entry_points.txt
tracery3-1.0.1.dist-info/top_level.txt
tracery3-1.0.1.dist-info/RECORD
