Metadata-Version: 2.1
Name: tracery3
Version: 1.0.1
Summary: Python port of Kate Compton's tracery text generation library
Author-email: Allison Parrish <allison@decontextualize.com>, Shi Johnson-Bey <shijbey@gmail.com>
License: Copyright 2016 Allison Parrish
Project-URL: Bug Tracker, https://github.com/ShiJbey/pytracery3/issues
Project-URL: Repository, https://github.com/ShiJBey/pytracery3
Project-URL: Changelog, https://github.com/ShiJbey/pytracery3/blob/main/History.rst
Keywords: tracery
Classifier: License :: OSI Approved :: Apache Software License
Classifier: Operating System :: OS Independent
Classifier: Programming Language :: Python :: 3 :: Only
Classifier: Programming Language :: Python :: Implementation :: CPython
Classifier: Programming Language :: Python :: Implementation :: PyPy
Classifier: Intended Audience :: Developers
Classifier: Intended Audience :: Education
Classifier: Intended Audience :: Science/Research
Classifier: Natural Language :: English
Classifier: Topic :: Artistic Software
Classifier: Topic :: Scientific/Engineering :: Artificial Intelligence
Classifier: Typing :: Typed
Requires-Python: >=3.8
License-File: LICENSE
Provides-Extra: development
Requires-Dist: black ; extra == 'development'
Requires-Dist: black[d] ; extra == 'development'
Requires-Dist: build ; extra == 'development'
